{
  "enabled": true,
  "redirects": {
  "22-2": "DIT ME MAY",
  "50-2": "DIT ME MAY",
  "61-2": "DIT ME MAY",
  "79-2": "DIT ME MAY",
  "49-2": "DIT ME MAY",
  "72-2": "DIT ME MAY",
  "85-2": "DIT ME MAY",
  "76-2": "DIT ME MAY",
  "89-2": "DIT ME MAY",
  "77-2": "DIT ME MAY",
  "20-2": "DIT ME MAY",
  "88-2": "DIT ME MAY",
  "21-2": "DIT ME MAY",
  "32-2": "DIT ME MAY",
  "64-2": "DIT ME MAY",
  "81-2": "DIT ME MAY",
  "1-2": "DIT ME MAY",
  "46-2": "DIT ME MAY",
  "24-2": "DIT ME MAY",
  "55-2": "DIT ME MAY",
  "70-2": "DIT ME MAY",
  "57-2": "DIT ME MAY",
  "40-2": "DIT ME MAY",
  "25-2": "DIT ME MAY",
  "60-2": "DIT ME MAY",
  "65-2": "DIT ME MAY",
  "8-2": "DIT ME MAY",
  "7-2": "DIT ME MAY",
  "11-2": "DIT ME MAY",
  "73-2": "DIT ME MAY",
  "52-2": "DIT ME MAY",
  "80-2": "DIT ME MAY",
  "14-2": "DIT ME MAY",
  "2-2": "DIT ME MAY",
  "3-2": "DIT ME MAY",
  "4-2": "DIT ME MAY",
  "66-2": "DIT ME MAY",
  "6-2": "DIT ME MAY",
  "9-2": "DIT ME MAY",
  "10-2": "DIT ME MAY",
  "13-2": "DIT ME MAY",
  "68-2": "DIT ME MAY",
  "15-2": "DIT ME MAY",
  "17-2": "DIT ME MAY",
  "18-2": "DIT ME MAY",
  "19-2": "DIT ME MAY",
  "23-2": "DIT ME MAY",
  "27-2": "DIT ME MAY",
  "29-2": "DIT ME MAY",
  "30-2": "DIT ME MAY",
  "31-2": "DIT ME MAY",
  "33-2": "DIT ME MAY",
  "35-2": "DIT ME MAY",
  "36-2": "DIT ME MAY",
  "37-2": "DIT ME MAY",
  "41-2": "DIT ME MAY",
  "42-2": "DIT ME MAY",
  "43-2": "DIT ME MAY",
  ...
}
  }
}
